{
  "version": "1.0",
  "exportedAt": "2025-10-04T15:59:46.621Z",
  "texts": [
    {
      "id": "0d8ac9ad-1cee-42a5-8d02-584dccb8b2cc",
      "title": "平家物語",
      "author": "作者不詳",
      "content": "祇園精舎の鐘の声、諸行無常の響きあり。娑羅双樹の花の色、盛者必衰の理をあらはす。おごれる人も久しからず、ただ春の夜の夢のごとし。たけき者もついにはほろびぬ、ひとへに風の前の塵に同じ。\n\n遠く異朝をとぶらへば、秦の趙高、漢の王莽、梁の朱伊、唐の禄山、これらは皆、旧主先皇の政にもしたがはず、楽しみをきはめ、諫めをも思ひいれず、天下の乱れむことを悟らずして、民間の愁ふるところを知らざつしかば、久しからずして、亡じにし者どもなり。\n\n近く本朝をうかがふに、承平の将門、天慶の純友、康和の義親、平治の信頼、これらはおごれる心もたけきことも、皆とりどりにこそありしかども、まぢかくは六波羅の入道前太政大臣平朝臣清盛公と申しし人のありさま、伝え承るこそ、心もことばも及ばれね。\n\nその先祖を尋ぬれば、桓武天皇第五の皇子、一品式部卿葛原親王九代の後胤、讃岐守正盛が孫、刑部卿忠盛朝臣の嫡男なり。かの親王の御子、高視の王、無官無位にして失せ給ひぬ。その御子高望の王の時、初めて平の姓を賜はつて、上総介になり給ひしより、たちまちに王氏を出でて、人臣につらなる。",
      "isCustom": false,
      "createdAt": "2025-10-02T16:23:54.920Z"
    }
  ]
}